drive_catalog/__init__.py
drive_catalog/console.py
drive_catalog/driveinfo.py
drive_catalog/fileinfo.py
drive_catalog-0.2.0.dist-info/LICENSE
drive_catalog-0.2.0.dist-info/METADATA
drive_catalog-0.2.0.dist-info/WHEEL
drive_catalog-0.2.0.dist-info/entry_points.txt
drive_catalog-0.2.0.dist-info/top_level.txt
drive_catalog-0.2.0.dist-info/RECORD
