Metadata-Version: 2.1
Name: drive-catalog
Version: 0.2.0
Summary: Return formatted file and directory information.
Home-page: https://bitbucket.com/bestep/drive-catalog
Author: William Estep
License: UNKNOWN
Platform: UNKNOWN
Classifier: Programming Language :: Python :: 3.8
Classifier: Topic :: Utilities
Classifier: License :: OSI Approved :: GNU Affero General Public License v3 or later (AGPLv3+)
Requires-Python: >=3.7
Requires-Dist: setuptools
Provides-Extra: lint
Requires-Dist: flake8 (>=3.5.0) ; extra == 'lint'
Provides-Extra: test
Requires-Dist: pytest ; extra == 'test'
Requires-Dist: pytest-cov ; extra == 'test'
